dcard/__init__.py
dcard/base_classes.py
dcard/extceptions.py
dcard/wrapper.py
dcard/actions/__init__.py
dcard/actions/create_card_request.py
dcard/actions/deny_card.py
dcard/actions/download.py
dcard/actions/list_cities.py
dcard/actions/list_tires.py
dcard/actions/print_card.py
dcard/actions/push_card.py
dcard/actions/retrieve_card_request.py
dcard/actions/update_card.py
dcard_sdk-0.1.5.dist-info/LICENCE.txt
dcard_sdk-0.1.5.dist-info/METADATA
dcard_sdk-0.1.5.dist-info/WHEEL
dcard_sdk-0.1.5.dist-info/top_level.txt
dcard_sdk-0.1.5.dist-info/RECORD
