Metadata-Version: 2.1
Name: dcard-sdk
Version: 0.1.5
Summary: UNKNOWN
Home-page: UNKNOWN
Author: Pech Kirill
Author-email: pechkirill@gmail.com
License: MIT
Platform: UNKNOWN
Requires-Python: >=3.7
Requires-Dist: schema (==0.7.0)
Requires-Dist: requests (==2.22.0)
